[
  {
    "ContainingType": "SnakesMaster.API.Controllers.HighScoreController",
    "Method": "CreateHighScore",
    "RelativePath": "api/HighScore/CreateHighScore",
    "HttpMethod": "POST",
    "IsController": true,
    "Order": 0,
    "Parameters": [
      {
        "Name": "request",
        "Type": "CreateHighScoreRequest",
        "IsRequired": true
      }
    ],
    "ReturnTypes": [
      {
        "Type": "CreateHighScoreResponse",
        "MediaTypes": [
          "text/plain",
          "application/json",
          "text/json"
        ],
        "StatusCode": 200
      }
    ]
  },
  {
    "ContainingType": "SnakesMaster.API.Controllers.HighScoreController",
    "Method": "DeleteHighScore",
    "RelativePath": "api/HighScore/DeleteHighScore/{publicIdentifier}",
    "HttpMethod": "DELETE",
    "IsController": true,
    "Order": 0,
    "Parameters": [
      {
        "Name": "publicIdentifier",
        "Type": "System.Guid",
        "IsRequired": true
      }
    ],
    "ReturnTypes": []
  },
  {
    "ContainingType": "SnakesMaster.API.Controllers.HighScoreController",
    "Method": "GetHighScoreById",
    "RelativePath": "api/HighScore/GetHighScoreById/{publicIdentifier}",
    "HttpMethod": "GET",
    "IsController": true,
    "Order": 0,
    "Parameters": [
      {
        "Name": "publicIdentifier",
        "Type": "System.Guid",
        "IsRequired": true
      }
    ],
    "ReturnTypes": [
      {
        "Type": "GetHighScoresResponse",
        "MediaTypes": [
          "text/plain",
          "application/json",
          "text/json"
        ],
        "StatusCode": 200
      }
    ]
  },
  {
    "ContainingType": "SnakesMaster.API.Controllers.HighScoreController",
    "Method": "GetHighScores",
    "RelativePath": "api/HighScore/GetHighScores",
    "HttpMethod": "GET",
    "IsController": true,
    "Order": 0,
    "Parameters": [
      {
        "Name": "page",
        "Type": "System.Int32",
        "IsRequired": false
      },
      {
        "Name": "pageSize",
        "Type": "System.Int32",
        "IsRequired": false
      }
    ],
    "ReturnTypes": [
      {
        "Type": "System.Collections.Generic.IEnumerable\u00601[[GetHighScoresResponse, SnakesMaster.API, Version=1.0.0.0, Culture=neutral, PublicKeyToken=null]]",
        "MediaTypes": [
          "text/plain",
          "application/json",
          "text/json"
        ],
        "StatusCode": 200
      }
    ]
  },
  {
    "ContainingType": "SnakesMaster.API.Controllers.HighScoreController",
    "Method": "UpdateHighScore",
    "RelativePath": "api/HighScore/UpdateHighScore/{publicIdentifier}",
    "HttpMethod": "PUT",
    "IsController": true,
    "Order": 0,
    "Parameters": [
      {
        "Name": "publicIdentifier",
        "Type": "System.Guid",
        "IsRequired": true
      },
      {
        "Name": "request",
        "Type": "CreateHighScoreRequest",
        "IsRequired": true
      }
    ],
    "ReturnTypes": []
  },
  {
    "ContainingType": "SnakesMaster.API.Controllers.UserController",
    "Method": "CreateOrGetUser",
    "RelativePath": "api/User/CreateOrGetUser",
    "HttpMethod": "POST",
    "IsController": true,
    "Order": 0,
    "Parameters": [
      {
        "Name": "userDetails",
        "Type": "SnakesMaster.API.DTOs.User.CreateUserRequest",
        "IsRequired": true
      }
    ],
    "ReturnTypes": [
      {
        "Type": "SnakesMaster.API.DTOs.User.UserDetailsResponse",
        "MediaTypes": [
          "text/plain",
          "application/json",
          "text/json"
        ],
        "StatusCode": 200
      }
    ]
  },
  {
    "ContainingType": "SnakesMaster.API.Controllers.UserController",
    "Method": "DeleteUser",
    "RelativePath": "api/User/DeleteUser/{id}",
    "HttpMethod": "DELETE",
    "IsController": true,
    "Order": 0,
    "Parameters": [
      {
        "Name": "id",
        "Type": "System.Guid",
        "IsRequired": true
      }
    ],
    "ReturnTypes": []
  },
  {
    "ContainingType": "SnakesMaster.API.Controllers.UserController",
    "Method": "GetUserById",
    "RelativePath": "api/User/GetUserById/{id}",
    "HttpMethod": "GET",
    "IsController": true,
    "Order": 0,
    "Parameters": [
      {
        "Name": "id",
        "Type": "System.Guid",
        "IsRequired": true
      }
    ],
    "ReturnTypes": [
      {
        "Type": "SnakesMaster.API.DTOs.User.UserDetailsResponse",
        "MediaTypes": [
          "text/plain",
          "application/json",
          "text/json"
        ],
        "StatusCode": 200
      }
    ]
  },
  {
    "ContainingType": "SnakesMaster.API.Controllers.UserController",
    "Method": "UpdateUser",
    "RelativePath": "api/User/UpdateUser",
    "HttpMethod": "PUT",
    "IsController": true,
    "Order": 0,
    "Parameters": [
      {
        "Name": "userDetails",
        "Type": "SnakesMaster.API.DTOs.User.UpdateUserRequest",
        "IsRequired": true
      }
    ],
    "ReturnTypes": [
      {
        "Type": "SnakesMaster.API.DTOs.User.UserDetailsResponse",
        "MediaTypes": [
          "text/plain",
          "application/json",
          "text/json"
        ],
        "StatusCode": 200
      }
    ]
  }
]